{
    "race": [
        {
            "category": "White",
            "Ward 29 Pop": 9894,
            "Ward 29 Part": 0.01,
            "Ward 35 Pop": 11182,
            "Ward 35 Part": 0.01,
            "Ward 36 Pop": 12995,
            "Ward 36 Part": 0.01,
            "Ward 49 Pop": 21968,
            "Ward 49 Part": 0.03
        },
        {
            "category": "Black",
            "Ward 29 Pop": 36857,
            "Ward 29 Part": 0.03,
            "Ward 35 Pop": 1872,
            "Ward 35 Part": 0.00,
            "Ward 36 Pop": 1605,
            "Ward 36 Part": 0.00,
            "Ward 49 Pop": 13277,
            "Ward 49 Part": 0.02
        },
        {
            "category": "Asian",
            "Ward 29 Pop": 636,
            "Ward 29 Part": 0.00,
            "Ward 35 Pop": 2913,
            "Ward 35 Part": 0.00,
            "Ward 36 Pop": 1294,
            "Ward 36 Part": 0.00,
            "Ward 49 Pop": 3892,
            "Ward 49 Part": 0.01
        },
        {
            "category": "Latino",
            "Ward 29 Pop": 10010,
            "Ward 29 Part": 0.01,
            "Ward 35 Pop": 35314,
            "Ward 35 Part": 0.04,
            "Ward 36 Pop": 35463,
            "Ward 36 Part": 0.03,
            "Ward 49 Pop": 12477,
            "Ward 49 Part": 0.02
        },
        {
            "category": "Other",
            "Ward 29 Pop": 463,
            "Ward 29 Part": 0.00,
            "Ward 35 Pop": 728,
            "Ward 35 Part": 0.00,
            "Ward 36 Pop": 414,
            "Ward 36 Part": 0.00,
            "Ward 49 Pop": 1706,
            "Ward 49 Part": 0.00
        }
    ],
    "income": [
        {
            "category": "< $10,000",
            "Ward 29 Pop": 7522,
            "Ward 29 Part": 0.01,
            "Ward 35 Pop": 4161,
            "Ward 35 Part": 0.00,
            "Ward 36 Pop": 3106,
            "Ward 36 Part": 0.00,
            "Ward 49 Pop": 6932,
            "Ward 49 Part": 0.01
        },
        {
            "category": "$10,000-24,999",
            "Ward 29 Pop": 12729,
            "Ward 29 Part": 0.01,
            "Ward 35 Pop": 9882,
            "Ward 35 Part": 0.01,
            "Ward 36 Pop": 8801,
            "Ward 36 Part": 0.01,
            "Ward 49 Pop": 11731,
            "Ward 49 Part": 0.02
        },
        {
            "category": "$25,000-39,999",
            "Ward 29 Pop": 10993,
            "Ward 29 Part": 0.01,
            "Ward 35 Pop": 9362,
            "Ward 35 Part": 0.01,
            "Ward 36 Pop": 10354,
            "Ward 36 Part": 0.01,
            "Ward 49 Pop": 9598,
            "Ward 49 Part": 0.01
        },
        {
            "category": "$40,000-59,999",
            "Ward 29 Pop": 8679,
            "Ward 29 Part": 0.01,
            "Ward 35 Pop": 9362,
            "Ward 35 Part": 0.01,
            "Ward 36 Pop": 10354,
            "Ward 36 Part": 0.01,
            "Ward 49 Pop": 8531,
            "Ward 49 Part": 0.01
        },
        {
            "category": "$60,000-99,999",
            "Ward 29 Pop": 9836,
            "Ward 29 Part": 0.01,
            "Ward 35 Pop": 10922,
            "Ward 35 Part": 0.01,
            "Ward 36 Pop": 10354,
            "Ward 36 Part": 0.01,
            "Ward 49 Pop": 9598,
            "Ward 49 Part": 0.01
        },
        {
            "category": "$100,000-149,999",
            "Ward 29 Pop": 5786,
            "Ward 29 Part": 0.00,
            "Ward 35 Pop": 5721,
            "Ward 35 Part": 0.01,
            "Ward 36 Pop": 6213,
            "Ward 36 Part": 0.01,
            "Ward 49 Pop": 4266,
            "Ward 49 Part": 0.01
        },
        {
            "category": "> $150,000",
            "Ward 29 Pop": 2314,
            "Ward 29 Part": 0.00,
            "Ward 35 Pop": 3121,
            "Ward 35 Part": 0.00,
            "Ward 36 Pop": 2589,
            "Ward 36 Part": 0.00,
            "Ward 49 Pop": 2666,
            "Ward 49 Part": 0.00
        }
    ],
    "educ": [
        {
            "category": "Less than high school",
            "Ward 29 Pop": 11341,
            "Ward 29 Part": 0.01,
            "Ward 35 Pop": 15447,
            "Ward 35 Part": 0.02,
            "Ward 36 Pop": 16463,
            "Ward 36 Part": 0.02,
            "Ward 49 Pop": 8371,
            "Ward 49 Part": 0.01
        },
        {
            "category": "High school",
            "Ward 29 Pop": 19904,
            "Ward 29 Part": 0.02,
            "Ward 35 Pop": 13054,
            "Ward 35 Part": 0.02,
            "Ward 36 Pop": 311,
            "Ward 36 Part": 0.02,
            "Ward 49 Pop": 10131,
            "Ward 49 Part": 0.01
        },
        {
            "category": "Some college",
            "Ward 29 Pop": 16837,
            "Ward 29 Part": 0.01,
            "Ward 35 Pop": 10610,
            "Ward 35 Part": 0.01,
            "Ward 36 Pop": 11856,
            "Ward 36 Part": 0.01,
            "Ward 49 Pop": 12584,
            "Ward 49 Part": 0.02
        },
        {
            "category": "Professional school",
            "Ward 29 Pop": 405,
            "Ward 29 Part": 0.00,
            "Ward 35 Pop": 572,
            "Ward 35 Part": 0.00,
            "Ward 36 Pop": 259,
            "Ward 36 Part": 0.00,
            "Ward 49 Pop": 1226,
            "Ward 49 Part": 0.00
        },
        {
            "category": "Bachelor",
            "Ward 29 Pop": 6191,
            "Ward 29 Part": 0.01,
            "Ward 35 Pop": 9154,
            "Ward 35 Part": 0.01,
            "Ward 36 Pop": 5281,
            "Ward 36 Part": 0.01,
            "Ward 49 Pop": 13384,
            "Ward 49 Part": 0.02
        },
        {
            "category": "Master",
            "Ward 29 Pop": 3124,
            "Ward 29 Part": 0.00,
            "Ward 35 Pop": 2965,
            "Ward 35 Part": 0.00,
            "Ward 36 Pop": 1967,
            "Ward 36 Part": 0.00,
            "Ward 49 Pop": 6558,
            "Ward 49 Part": 0.01
        },
        {
            "category": "Doctorate",
            "Ward 29 Pop": 58,
            "Ward 29 Part": 0.00,
            "Ward 35 Pop": 208,
            "Ward 35 Part": 0.00,
            "Ward 36 Pop": 311,
            "Ward 36 Part": 0.00,
            "Ward 49 Pop": 1066,
            "Ward 49 Part": 0.00
        }
    ]
}